Jinja2Filters/duration_as.py
Jinja2Filters/pad.py
Jinja2Filters/strftime.py
cylc/__init__.py
cylc/batch_sys_manager.py
cylc/broadcast_mgr.py
cylc/broadcast_report.py
cylc/c3mro.py
cylc/cfgvalidate.py
cylc/command_polling.py
cylc/conditional_simplifier.py
cylc/config.py
cylc/cylc_subproc.py
cylc/daemonize.py
cylc/dbstatecheck.py
cylc/dump.py
cylc/exceptions.py
cylc/flags.py
cylc/graph_parser.py
cylc/graphnode.py
cylc/host_appointer.py
cylc/hostuserutil.py
cylc/job.sh
cylc/job_file.py
cylc/log_diagnosis.py
cylc/loggingutil.py
cylc/option_parsers.py
cylc/param_expand.py
cylc/prerequisite.py
cylc/print_tree.py
cylc/profiler.py
cylc/remote.py
cylc/run_get_stdout.py
cylc/rundb.py
cylc/scheduler.py
cylc/scheduler_cli.py
cylc/state_summary_mgr.py
cylc/subprocctx.py
cylc/subprocpool.py
cylc/suite_db_mgr.py
cylc/suite_events.py
cylc/suite_srv_files_mgr.py
cylc/suite_status.py
cylc/task_action_timer.py
cylc/task_events_mgr.py
cylc/task_id.py
cylc/task_job_logs.py
cylc/task_job_mgr.py
cylc/task_message.py
cylc/task_outputs.py
cylc/task_pool.py
cylc/task_proxy.py
cylc/task_remote_cmd.py
cylc/task_remote_mgr.py
cylc/task_state.py
cylc/task_state_prop.py
cylc/task_trigger.py
cylc/taskdef.py
cylc/templatevars.py
cylc/terminal.py
cylc/time_parser.py
cylc/wallclock.py
cylc/xtrigger_mgr.py
cylc/batch_sys_handlers/__init__.py
cylc/batch_sys_handlers/at.py
cylc/batch_sys_handlers/background.py
cylc/batch_sys_handlers/loadleveler.py
cylc/batch_sys_handlers/lsf.py
cylc/batch_sys_handlers/moab.py
cylc/batch_sys_handlers/pbs.py
cylc/batch_sys_handlers/pbs_multi_cluster.py
cylc/batch_sys_handlers/sge.py
cylc/batch_sys_handlers/slurm.py
cylc/cfgspec/__init__.py
cylc/cfgspec/glbl_cfg.py
cylc/cfgspec/globalcfg.py
cylc/cfgspec/suite.py
cylc/cycling/__init__.py
cylc/cycling/integer.py
cylc/cycling/iso8601.py
cylc/cycling/loader.py
cylc/cycling/util.py
cylc/network/__init__.py
cylc/network/client.py
cylc/network/scan.py
cylc/network/server.py
cylc/tests/__init__.py
cylc/tests/test_c3mro.py
cylc-8.0a0.dist-info/COPYING
cylc-8.0a0.dist-info/METADATA
cylc-8.0a0.dist-info/WHEEL
cylc-8.0a0.dist-info/top_level.txt
cylc-8.0a0.dist-info/RECORD
