Metadata-Version: 2.1
Name: cylc
Version: 8.0a0
Summary: 
Requires-Dist: colorama (==0.4.*)
Requires-Dist: isodatetime (==1!2.0.*)
Requires-Dist: jinja2 (<2.11.0,>=2.10.1)
Requires-Dist: markupsafe (==1.1.*)
Requires-Dist: python-jose (==3.0.*)
Requires-Dist: pyzmq (==18.0.*)
Provides-Extra: all
Requires-Dist: EmPy (==3.3.*) ; extra == 'all'
Requires-Dist: sphinx (==2.0.*) ; extra == 'all'
Requires-Dist: codecov (==2.0.*) ; extra == 'all'
Requires-Dist: coverage (==4.5.*) ; extra == 'all'
Requires-Dist: pytest-cov (==2.6.*) ; extra == 'all'
Requires-Dist: pytest (==4.4.*) ; extra == 'all'
Requires-Dist: pycodestyle (==2.5.*) ; extra == 'all'
Requires-Dist: testfixtures (==6.6.*) ; extra == 'all'
Provides-Extra: docs
Requires-Dist: sphinx (==2.0.*) ; extra == 'docs'
Provides-Extra: empy
Requires-Dist: EmPy (==3.3.*) ; extra == 'empy'
